transkribus/__init__.py
transkribus/api.py
transkribus/models.py
transkribus/pagexml.py
transkribus/utils.py
transkribus/xml.py
transkribus_client-0.3.3.dist-info/LICENSE
transkribus_client-0.3.3.dist-info/METADATA
transkribus_client-0.3.3.dist-info/WHEEL
transkribus_client-0.3.3.dist-info/top_level.txt
transkribus_client-0.3.3.dist-info/RECORD
