Metadata-Version: 2.1
Name: transkribus-client
Version: 0.3.3
Summary: Unofficial API client for the Transkribus project
Home-page: https://gitlab.com/teklia/arkindex/transkribus
Author: Teklia <contact@teklia.com>
License: MIT
Keywords: api client transkribus
Platform: UNKNOWN
Classifier: License :: OSI Approved :: MIT License
Classifier: Natural Language :: English
Classifier: Intended Audience :: Science/Research
Classifier: Programming Language :: Python :: 3
Classifier: Programming Language :: Python :: 3 :: Only
Classifier: Programming Language :: Python :: 3.6
Classifier: Programming Language :: Python :: 3.7
Classifier: Programming Language :: Python :: 3.8
Classifier: Programming Language :: Python :: 3.9
Classifier: Programming Language :: Python :: 3.10
Classifier: Topic :: Scientific/Engineering :: Image Recognition
Classifier: Topic :: Text Processing :: Indexing
Classifier: Topic :: Text Processing :: Linguistic
Requires-Python: >=3.6
License-File: LICENSE
Requires-Dist: humanize (==4.3.0)
Requires-Dist: lxml (==4.6.3)
Requires-Dist: requests (==2.28.1)
